{
  "version": 6,
  "entities": [
    {
      "entity": {
        "type": "Project",
        "id": "636658d2-960c-45e5-bcc4-f6e9afeaaae2",
        "name": "FBI-App"
      },
      "children": [
        {
          "entity": {
            "type": "Request",
            "method": {
              "link": "http://tools.ietf.org/html/rfc7231#section-4.3.1",
              "name": "GET"
            },
            "body": {
              "formBody": {
                "overrideContentType": true,
                "encoding": "application/x-www-form-urlencoded",
                "items": []
              },
              "bodyType": "Text"
            },
            "uri": {
              "query": {
                "delimiter": "&",
                "items": []
              },
              "scheme": {
                "name": "http",
                "version": "V11"
              },
              "host": "localhost:9090",
              "path": "/mafia/bosses/Fat"
            },
            "id": "32ebd35b-c4da-4b8d-ad50-9995d9988b64",
            "name": "/bosses/bossId - OK",
            "headers": []
          }
        },
        {
          "entity": {
            "type": "Request",
            "method": {
              "link": "http://tools.ietf.org/html/rfc7231#section-4.3.1",
              "name": "GET"
            },
            "body": {
              "formBody": {
                "overrideContentType": true,
                "encoding": "application/x-www-form-urlencoded",
                "items": []
              },
              "bodyType": "Text"
            },
            "uri": {
              "query": {
                "delimiter": "&",
                "items": []
              },
              "scheme": {
                "name": "http",
                "version": "V11"
              },
              "host": "localhost:9090",
              "path": "/mafia/bosses/Italy"
            },
            "id": "8219e98f-e3b7-4fb6-8284-474d1dbcdf96",
            "name": "/bosses/{bossId} - NOT A BOSS",
            "headers": []
          }
        },
        {
          "entity": {
            "type": "Request",
            "method": {
              "link": "http://tools.ietf.org/html/rfc7231#section-4.3.1",
              "name": "GET"
            },
            "body": {
              "formBody": {
                "overrideContentType": true,
                "encoding": "application/x-www-form-urlencoded",
                "items": []
              },
              "bodyType": "Text"
            },
            "uri": {
              "query": {
                "delimiter": "&",
                "items": []
              },
              "scheme": {
                "name": "http",
                "version": "V11"
              },
              "host": "localhost:9090",
              "path": "/mafia/court/Fat/imprison"
            },
            "id": "d2ed3159-c229-40ce-b4c5-e629568704a3",
            "name": "/court/{bossId}/imprison",
            "headers": []
          }
        },
        {
          "entity": {
            "type": "Request",
            "method": {
              "link": "http://tools.ietf.org/html/rfc7231#section-4.3.1",
              "name": "GET"
            },
            "body": {
              "formBody": {
                "overrideContentType": true,
                "encoding": "application/x-www-form-urlencoded",
                "items": []
              },
              "bodyType": "Text"
            },
            "uri": {
              "query": {
                "delimiter": "&",
                "items": []
              },
              "scheme": {
                "name": "http",
                "version": "V11"
              },
              "host": "localhost:9090",
              "path": "/mafia/court/Fat/release"
            },
            "id": "f69bbbf3-28c8-48e2-9859-4d495a82ac34",
            "name": "/court/{bossId}/release",
            "headers": []
          }
        },
        {
          "entity": {
            "type": "Request",
            "method": {
              "link": "http://tools.ietf.org/html/rfc7231#section-4.3.1",
              "name": "GET"
            },
            "body": {
              "formBody": {
                "overrideContentType": true,
                "encoding": "application/x-www-form-urlencoded",
                "items": []
              },
              "bodyType": "Text"
            },
            "uri": {
              "query": {
                "delimiter": "&",
                "items": []
              },
              "scheme": {
                "name": "http",
                "version": "V11"
              },
              "host": "localhost:9090",
              "path": "/mafia/mobster/none"
            },
            "id": "6dff3b33-48cb-445b-9bc5-76b31b870974",
            "name": "/mobster/mobsterId - NOT FOUND",
            "headers": []
          }
        },
        {
          "entity": {
            "type": "Request",
            "method": {
              "link": "http://tools.ietf.org/html/rfc7231#section-4.3.1",
              "name": "GET"
            },
            "body": {
              "formBody": {
                "overrideContentType": true,
                "encoding": "application/x-www-form-urlencoded",
                "items": []
              },
              "bodyType": "Text"
            },
            "uri": {
              "query": {
                "delimiter": "&",
                "items": []
              },
              "scheme": {
                "name": "http",
                "version": "V11"
              },
              "host": "localhost:9090",
              "path": "/mafia/mobster/Italy"
            },
            "id": "7779430e-3dd6-4391-9738-93b9278c9602",
            "name": "/mobster/{mobsterId} - OK",
            "headers": []
          }
        },
        {
          "entity": {
            "type": "Request",
            "method": {
              "link": "http://tools.ietf.org/html/rfc7231#section-4.3.1",
              "name": "GET"
            },
            "body": {
              "formBody": {
                "overrideContentType": true,
                "encoding": "application/x-www-form-urlencoded",
                "items": []
              },
              "bodyType": "Text"
            },
            "uri": {
              "query": {
                "delimiter": "&",
                "items": []
              },
              "scheme": {
                "name": "http",
                "version": "V11"
              },
              "host": "localhost:9090",
              "path": "/gitinformation"
            },
            "id": "8b16c0f2-5eb4-4dcd-a81b-7537a4079652",
            "name": "GitInformation",
            "headers": []
          }
        },
        {
          "entity": {
            "type": "Request",
            "method": {
              "link": "http://tools.ietf.org/html/rfc7231#section-4.3.1",
              "name": "GET"
            },
            "body": {
              "formBody": {
                "overrideContentType": true,
                "encoding": "application/x-www-form-urlencoded",
                "items": []
              },
              "bodyType": "Text"
            },
            "uri": {
              "query": {
                "delimiter": "&",
                "items": []
              },
              "scheme": {
                "name": "http",
                "version": "V11"
              },
              "host": "localhost:9090",
              "path": "/keepalive"
            },
            "id": "41546bdf-d5e8-49af-a62b-a4a4a106f58d",
            "name": "KeepAlive",
            "headers": []
          }
        }
      ]
    }
  ]
}